{
  "temperature": 2,
  "downfall": 0,
  "has_precipitation": false,
  "effects": {
    "sky_color": 6766205,
    "fog_color": 10239374,
    "water_color": 13441225,
    "water_fog_color": 7086177,
    "ambient_sound": "minecraft:ambient.warped_forest.loop",
    "particle": {
      "options": {
        "type": "minecraft:dragon_breath"
      },
      "probability": 0.00128
    }
  },
  "spawners": {
    "ambient": [],
    "axolotls": [],
    "creature": [],
    "misc": [],
    "monster": [],
    "underground_water_creature": [],
    "water_ambient": [],
    "water_creature": []
  },
  "spawn_costs": {},
  "carvers": {
    "air": "minecraft:nether_cave"
  },
  "features": [
    [],
    [],
    [],
    [],
    [],
    [],
    [],
    [],
    [
      "vpend:echoeing_wastelands_vegetation",
      "vpend:choir_bubbles"
    ],
    [
      "minecraft:chorus_plant"
    ]
  ]
}
  